dexviewer/__init__.py
dexviewer/__main__.py
dexviewer/bgPlotter.py
dexviewer/dexShareCredentials.py
dexviewer/dexViewer.py
dexviewer/utils.py
dexviewer/data/dexviewer.desktop
dexviewer/data/icons/dexviewer.png
dexviewer/data/icons/dexviewer.svg
dexviewer/data/styles/style.css
dexviewer-1.2.0.data/scripts/setup_dexviewer.sh
dexviewer-1.2.0.dist-info/LICENSE
dexviewer-1.2.0.dist-info/METADATA
dexviewer-1.2.0.dist-info/WHEEL
dexviewer-1.2.0.dist-info/entry_points.txt
dexviewer-1.2.0.dist-info/top_level.txt
dexviewer-1.2.0.dist-info/RECORD
