Metadata-Version: 2.1
Name: dexviewer
Version: 1.2.0
Summary: A GTK-4 interface for viewing Dexcom CGM data from the pydexcom API
Home-page: https://github.com/narmis-e/DexViewer
Author: Narmis-E
Author-email: narmisecurb@gmail.com
License: GPLv3
Classifier: Intended Audience :: End Users/Desktop
Classifier: License :: OSI Approved :: GNU General Public License v3 (GPLv3)
Classifier: Operating System :: POSIX :: Linux
Classifier: Programming Language :: Python :: 3
Classifier: Topic :: Desktop Environment
Classifier: Topic :: Utilities
License-File: LICENSE
Requires-Dist: PyGObject
Requires-Dist: pandas
Requires-Dist: pydexcom
Requires-Dist: matplotlib
